mp4_to_jpg_click-1.3.7.dist-info/METADATA
mp4_to_jpg_click-1.3.7.dist-info/WHEEL
mp4_to_jpg_click-1.3.7.dist-info/entry_points.txt
mp4_to_jpg_click-1.3.7.dist-info/licenses/LICENSE.txt
mp4_to_jpg_click/__init__.py
mp4_to_jpg_click/mp4_to_jpg.py
mp4_to_jpg_click-1.3.7.dist-info/RECORD
