Metadata-Version: 2.1
Name: mp4-to-jpg-click
Version: 1.3.7
Summary: A CLI tool to extract frames from MP4/MOV videos with intelligent frame skipping and duplicate detection
Keywords: video,frame extraction,mp4,jpg,cli
Author-Email: tadeasf <business@tadeasfort.com>
License: GPL-3.0
Classifier: Development Status :: 5 - Production/Stable
Classifier: Environment :: Console
Classifier: Intended Audience :: End Users/Desktop
Classifier: License :: OSI Approved :: MIT License
Classifier: Programming Language :: Python :: 3
Classifier: Programming Language :: Python :: 3.11
Classifier: Topic :: Multimedia :: Video
Classifier: Topic :: Utilities
Project-URL: Homepage, https://github.com/tadeasf/mp4-to-jpg-click
Project-URL: Repository, https://github.com/tadeasf/mp4-to-jpg-click
Requires-Python: >=3.11
Requires-Dist: opencv-python>=4.10.0.84
Requires-Dist: imagehash>=4.3.1
Requires-Dist: pillow>=11.0.0
Requires-Dist: loguru>=0.7.2
Requires-Dist: tqdm>=4.66.5
Requires-Dist: rich-click>=1.8.3
Requires-Dist: prompt-toolkit>=3.0.48
